flexlibs/__init__.py
flexlibs/code/FLExGlobals.py
flexlibs/code/FLExInit.py
flexlibs/code/FLExLCM.py
flexlibs/code/FLExProject.py
flexlibs/code/__init__.py
flexlibs/docs/flexlibsAPI/.buildinfo
flexlibs/docs/flexlibsAPI/flexlibs.html
flexlibs/docs/flexlibsAPI/objects.inv
flexlibs/docs/flexlibsAPI/search.html
flexlibs/docs/flexlibsAPI/searchindex.js
flexlibs/docs/flexlibsAPI/.doctrees/environment.pickle
flexlibs/docs/flexlibsAPI/.doctrees/flexlibs.doctree
flexlibs/docs/flexlibsAPI/_modules/index.html
flexlibs/docs/flexlibsAPI/_modules/flexlibs/code/FLExProject.html
flexlibs/docs/flexlibsAPI/_static/basic.css
flexlibs/docs/flexlibsAPI/_static/dialog-note.png
flexlibs/docs/flexlibsAPI/_static/dialog-seealso.png
flexlibs/docs/flexlibsAPI/_static/dialog-todo.png
flexlibs/docs/flexlibsAPI/_static/dialog-topic.png
flexlibs/docs/flexlibsAPI/_static/dialog-warning.png
flexlibs/docs/flexlibsAPI/_static/doctools.js
flexlibs/docs/flexlibsAPI/_static/documentation_options.js
flexlibs/docs/flexlibsAPI/_static/epub.css
flexlibs/docs/flexlibsAPI/_static/file.png
flexlibs/docs/flexlibsAPI/_static/footerbg.png
flexlibs/docs/flexlibsAPI/_static/headerbg.png
flexlibs/docs/flexlibsAPI/_static/ie6.css
flexlibs/docs/flexlibsAPI/_static/language_data.js
flexlibs/docs/flexlibsAPI/_static/middlebg.png
flexlibs/docs/flexlibsAPI/_static/minus.png
flexlibs/docs/flexlibsAPI/_static/plus.png
flexlibs/docs/flexlibsAPI/_static/pygments.css
flexlibs/docs/flexlibsAPI/_static/pyramid.css
flexlibs/docs/flexlibsAPI/_static/searchtools.js
flexlibs/docs/flexlibsAPI/_static/sphinx_highlight.js
flexlibs/docs/flexlibsAPI/_static/transparent.gif
flexlibs/examples/demo_lexicon.py
flexlibs/examples/demo_openproject.py
flexlibs/tests/test_CustomFields.py
flexlibs/tests/test_FLExInit.py
flexlibs/tests/test_FLExProject.py
flexlibs-1.2.8.dist-info/licenses/LICENSE.txt
flexlibs-1.2.8.dist-info/METADATA
flexlibs-1.2.8.dist-info/WHEEL
flexlibs-1.2.8.dist-info/top_level.txt
flexlibs-1.2.8.dist-info/RECORD
