Metadata-Version: 2.4
Name: flexlibs
Version: 1.2.8
Summary: A library for accessing FieldWorks Language Explorer projects
Home-page: https://github.com/cdfarrow/flexlibs/wiki
Author: Craig Farrow
Author-email: flextoolshelp@gmail.com
License: "GPL-2.0-or-later"
Platform: 'Windows'
Classifier: Intended Audience :: Developers
Classifier: Programming Language :: Python :: 3.8
Classifier: Programming Language :: Python :: 3.9
Classifier: Programming Language :: Python :: 3.10
Classifier: Programming Language :: Python :: 3.11
Classifier: Programming Language :: Python :: 3.12
Classifier: Programming Language :: Python :: 3.13
Classifier: Topic :: Text Processing :: Linguistic
Classifier: Topic :: Database
Requires-Python: <3.14,>=3.8
License-File: LICENSE.txt
Requires-Dist: pythonnet<3.1,>=3.0.3
Dynamic: license-file
